scLift/__init__.py
scLift/file/__init__.py
scLift/file/_read_.py
scLift/file/_write_.py
scLift/model/__init__.py
scLift/model/_core_.py
scLift/plot/__init__.py
scLift/plot/_bar_.py
scLift/plot/_barcode_.py
scLift/plot/_box_.py
scLift/plot/_bubble_.py
scLift/plot/_core_.py
scLift/plot/_graph_.py
scLift/plot/_heat_map_.py
scLift/plot/_kde_.py
scLift/plot/_line_.py
scLift/plot/_pie_.py
scLift/plot/_radar_.py
scLift/plot/_scatter_.py
scLift/plot/_venn_.py
scLift/plot/_violin_.py
scLift/preprocessing/__init__.py
scLift/preprocessing/_anndata_.py
scLift/preprocessing/_gencode_.py
scLift/preprocessing/_gsea_.py
scLift/preprocessing/_scanpy_.py
scLift/preprocessing/_scvi_.py
scLift/preprocessing/_snapatac_.py
scLift/tool/__init__.py
scLift/tool/_algorithm_.py
scLift/util/__init__.py
scLift/util/_constant_.py
scLift/util/_core_.py
sclift-0.0.63.dist-info/METADATA
sclift-0.0.63.dist-info/WHEEL
sclift-0.0.63.dist-info/licenses/LICENSE
sclift-0.0.63.dist-info/RECORD
