Metadata-Version: 2.4
Name: scLift
Version: 0.0.63
Summary: SCIV: Unveiling the pivotal cell types involved in variant function regulation at a single-cell resolution
Project-URL: gitee, https://gitee.com/ykenan_yingying/scLift
Author-email: Zhengmin Yu <yuzmbio@163.com>
License: Copyright (c) 2024 Zheng-Min Yu
License-File: LICENSE
Keywords: Causal variant,Fine-mapping,SCIV,Single-cell epiomics,scATAC-seq
Classifier: License :: OSI Approved :: MIT License
Classifier: Operating System :: OS Independent
Classifier: Programming Language :: Python :: 3
Requires-Python: >=3.10
Requires-Dist: anndata==0.9.1
Requires-Dist: colormap==1.0.4
Requires-Dist: easydev==0.13.2
Requires-Dist: gseapy==1.1.3
Requires-Dist: h5py==3.12.1
Requires-Dist: harmonypy==0.0.10
Requires-Dist: leidenalg==0.10.2
Requires-Dist: magic-impute==3.0.0
Requires-Dist: matplotlib-venn==1.1.2
Requires-Dist: matplotlib==3.7.1
Requires-Dist: mudata==0.2.3
Requires-Dist: networkx==3.3
Requires-Dist: numpy==1.26.4
Requires-Dist: palettable==3.3.3
Requires-Dist: pandas==1.5.3
Requires-Dist: pycomplexheatmap==1.6.1
Requires-Dist: scanpy==1.9.6
Requires-Dist: scikit-learn==1.5.2
Requires-Dist: scipy==1.14.1
Requires-Dist: scvi-tools==1.2.0
Requires-Dist: seaborn==0.11.2
Requires-Dist: statannotations==0.6.0
Requires-Dist: ykenan-file==0.2.8
Requires-Dist: ykenan-log==0.2.5
